posuto/__init__.py
posuto/postaldata.db
posuto/posuto.py
posuto/prep.py
posuto-2026.2.0.dist-info/licenses/LICENSE
posuto-2026.2.0.dist-info/METADATA
posuto-2026.2.0.dist-info/WHEEL
posuto-2026.2.0.dist-info/top_level.txt
posuto-2026.2.0.dist-info/RECORD
