Metadata-Version: 2.4
Name: posuto
Version: 2026.2.0
Summary: Japanese Postal Code Data
Home-page: https://github.com/polm/posuto.git
Author: Paul O'Leary McCann
Author-email: polm@dampfkraft.com
License: MIT
Classifier: Environment :: Console
Classifier: Intended Audience :: Developers
Classifier: Intended Audience :: Science/Research
Classifier: License :: OSI Approved :: MIT License
Classifier: Operating System :: POSIX :: Linux
Classifier: Operating System :: MacOS :: MacOS X
Classifier: Programming Language :: Python :: 3
License-File: LICENSE
Dynamic: author
Dynamic: author-email
Dynamic: home-page
Dynamic: license-file
Dynamic: summary
